starlette_prometheus/__init__.py
starlette_prometheus/middleware.py
starlette_prometheus/py.typed
starlette_prometheus/view.py
starlette_prometheus-0.9.0.dist-info/LICENSE
starlette_prometheus-0.9.0.dist-info/WHEEL
starlette_prometheus-0.9.0.dist-info/METADATA
starlette_prometheus-0.9.0.dist-info/RECORD
